cxmlinvbot/__init__.py
cxmlinvbot/kill.py
cxmlinvbot/main.py
cxmlinvbot/config/__init__.py
cxmlinvbot/config/base.py
cxmlinvbot/config/env.py
cxmlinvbot/config/mail.py
cxmlinvbot/errors/__init__.py
cxmlinvbot/errors/errors.py
cxmlinvbot/filing/__init__.py
cxmlinvbot/filing/filing.py
cxmlinvbot/mail/__init__.py
cxmlinvbot/mail/mail.py
cxmlinvbot/mapping/__init__.py
cxmlinvbot/mapping/action.py
cxmlinvbot/mapping/headermapping.py
cxmlinvbot/mapping/invoicedetailrequestmapping.py
cxmlinvbot/mapping/invoicedetailrequestservicemapping.py
cxmlinvbot/mapping/mapping.py
cxmlinvbot/mapping/profilerequestmapping.py
cxmlinvbot/objects/__init__.py
cxmlinvbot/objects/cxmlobject.py
cxmlinvbot/objects/profileresponse.py
cxmlinvbot/objects/response.py
cxmlinvbot/unittests/__init__.py
cxmlinvbot/unittests/test_action.py
cxmlinvbot/unittests/test_cxmlobject.py
cxmlinvbot/unittests/test_errors.py
cxmlinvbot/unittests/test_filing.py
cxmlinvbot/unittests/test_main.py
cxmlinvbot/unittests/test_mapping.py
cxmlinvbot/unittests/test_profileresponse.py
cxmlinvbot/unittests/test_response.py
objects/__init__.py
objects/cxmlobject.py
objects/profileresponse.py
objects/response.py
unittests/__init__.py
unittests/test_action.py
unittests/test_cxmlobject.py
unittests/test_errors.py
unittests/test_filing.py
unittests/test_mapping.py
unittests/test_profileresponse.py
unittests/test_response.py
cxmlinvbot-1.1.5.dist-info/METADATA
cxmlinvbot-1.1.5.dist-info/WHEEL
cxmlinvbot-1.1.5.dist-info/top_level.txt
cxmlinvbot-1.1.5.dist-info/RECORD
