Metadata-Version: 2.1
Name: cxmlinvbot
Version: 1.1.5
Summary: Invoice Bot - PO to Invoice in CXML
Author-email: monkeeferret@gmail.com
Requires-Python: >=3.11
Requires-Dist: lxml (>=4.9.2)
Requires-Dist: requests (>=2.29.0)
Requires-Dist: encrypta (>=1.0.0)
